app_kit/__init__.py
app_kit/admin.py
app_kit/admin_urls.py
app_kit/apps.py
app_kit/context_processors.py
app_kit/definitions.py
app_kit/forms.py
app_kit/generic.py
app_kit/generic_content_validation.py
app_kit/generic_content_zip_import.py
app_kit/global_urls.py
app_kit/middleware.py
app_kit/models.py
app_kit/permission_rules.py
app_kit/server_side_cursors.py
app_kit/settings.py
app_kit/urls.py
app_kit/utils.py
app_kit/validators.py
app_kit/view_mixins.py
app_kit/views.py
app_kit/app_kit_api/__init__.py
app_kit/app_kit_api/admin.py
app_kit/app_kit_api/apps.py
app_kit/app_kit_api/models.py
app_kit/app_kit_api/permissions.py
app_kit/app_kit_api/serializers.py
app_kit/app_kit_api/urls.py
app_kit/app_kit_api/views.py
app_kit/app_kit_api/migrations/0001_initial.py
app_kit/app_kit_api/migrations/__init__.py
app_kit/app_kit_api/tests/mixins.py
app_kit/app_kit_api/tests/test_serializers.py
app_kit/app_kit_api/tests/test_views.py
app_kit/app_kit_api/tests/__pycache__/mixins.cpython-311.pyc
app_kit/app_kit_api/tests/__pycache__/test_serializers.cpython-311.pyc
app_kit/app_kit_api/tests/__pycache__/test_views.cpython-311.pyc
app_kit/appbuilder/AppBuilderBase.py
app_kit/appbuilder/AppPreviewBuilder.py
app_kit/appbuilder/AppReleaseBuilder.py
app_kit/appbuilder/ContentImageBuilder.py
app_kit/appbuilder/GBIFlib.py
app_kit/appbuilder/TaxonBuilder.py
app_kit/appbuilder/__init__.py
app_kit/appbuilder/precompile_fulltree.py
app_kit/appbuilder/JSONBuilders/BackboneTaxonomyJSONBuilder.py
app_kit/appbuilder/JSONBuilders/ButtonMatrixJSONBuilder.py
app_kit/appbuilder/JSONBuilders/ContentImagesJSONBuilder.py
app_kit/appbuilder/JSONBuilders/FrontendJSONBuilder.py
app_kit/appbuilder/JSONBuilders/GenericFormJSONBuilder.py
app_kit/appbuilder/JSONBuilders/GlossaryJSONBuilder.py
app_kit/appbuilder/JSONBuilders/JSONBuilder.py
app_kit/appbuilder/JSONBuilders/MapJSONBuilder.py
app_kit/appbuilder/JSONBuilders/NatureGuideJSONBuilder.py
app_kit/appbuilder/JSONBuilders/TaxonProfilesJSONBuilder.py
localcosmos_app_kit-0.6.4.dist-info/licenses/LICENCE
localcosmos_app_kit-0.6.4.dist-info/METADATA
localcosmos_app_kit-0.6.4.dist-info/WHEEL
localcosmos_app_kit-0.6.4.dist-info/top_level.txt
localcosmos_app_kit-0.6.4.dist-info/RECORD
