Metadata-Version: 2.4
Name: localcosmos_app_kit
Version: 0.6.4
Summary: LocalCosmos App Kit. Web Portal to build Android and iOS apps
Home-page: https://github.com/localcosmos/app-kit
Author: Thomas Uher
Author-email: thomas.uher@sisol-systems.com
License: The MIT License
Keywords: django,localcosmos,localcosmos server,biodiversity
Platform: OS Independent
Classifier: Programming Language :: Python :: 3
Classifier: License :: OSI Approved :: MIT License
Classifier: Operating System :: OS Independent
Requires-Python: >=3.8
License-File: LICENCE
Requires-Dist: localcosmos-server==0.22.3
Requires-Dist: localcosmos-app-kit-taxonomy==0.2.1
Requires-Dist: localcosmos-cordova-builder==0.9.4
Requires-Dist: django-tenants==3.7.0
Requires-Dist: django-cleanup==9.0.0
Requires-Dist: django-ipware==7.0.1
Requires-Dist: django-filter==24.3
Requires-Dist: lxml
Requires-Dist: openpyxl==3.1.5
Requires-Dist: deepl
Requires-Dist: opencv-python
Requires-Dist: opencv-python-headless
Requires-Dist: unidecode
Dynamic: author
Dynamic: author-email
Dynamic: classifier
Dynamic: description
Dynamic: description-content-type
Dynamic: home-page
Dynamic: keywords
Dynamic: license
Dynamic: license-file
Dynamic: platform
Dynamic: requires-dist
Dynamic: requires-python
Dynamic: summary
